{
  "project": "harness_framework",
  "phase": "dashboard-records",
  "summary": "Complete the operator-facing dashboard and records flows, then document how to verify the local MVP end to end.",
  "completed_at": "2026-04-15T21:10:02+0900",
  "steps": [
    {
      "step": 0,
      "name": "build-dashboard-query-layer",
      "status": "completed",
      "summary": "Added organization-scoped dashboard query services for recent submissions, recent updates, pending sessions, and setup-gap detection.",
      "completed_at": "2026-04-15T21:10:02+0900"
    },
    {
      "step": 1,
      "name": "implement-dashboard-ui",
      "status": "completed",
      "summary": "Rebuilt /dashboard with messenger-like grouped panels for next actions, submission overview, recent submissions, updates, and pending sessions.",
      "completed_at": "2026-04-15T21:10:02+0900"
    },
    {
      "step": 2,
      "name": "implement-records-browser",
      "status": "completed",
      "summary": "Implemented /records list and detail views with search/status filtering and operator-only inspection of attendance, journal, and attachments.",
      "completed_at": "2026-04-15T21:10:02+0900"
    },
    {
      "step": 3,
      "name": "document-local-smoke-path",
      "status": "completed",
      "summary": "Documented the end-to-end local smoke path, including explicit attachment blocked behavior when storage bucket config is missing.",
      "completed_at": "2026-04-15T21:10:02+0900"
    }
  ]
}
